{
  "properties": [
    {
      "name": "app.auth.demo.username",
      "type": "java.lang.String",
      "description": "後台 Demo 帳號（開發用）。"
    },
    {
      "name": "app.auth.demo.password",
      "type": "java.lang.String",
      "description": "後台 Demo 密碼（開發用）。"
    },
    {
      "name": "app.auth.front.demo.username",
      "type": "java.lang.String",
      "description": "前台 Demo 帳號（開發用）。"
    },
    {
      "name": "app.auth.front.demo.password",
      "type": "java.lang.String",
      "description": "前台 Demo 密碼（開發用）。"
    },
    {
      "name": "app.auth.guard.enabled",
      "type": "java.lang.Boolean",
      "description": "是否啟用 API Auth Guard。"
    },
    {
      "name": "app.auth.guard.admin-path-prefixes",
      "type": "java.util.List<java.lang.String>",
      "description": "需後台登入的路徑前綴，符合任一即要求 ADMIN scope。"
    },
    {
      "name": "app.auth.guard.front-path-prefixes",
      "type": "java.util.List<java.lang.String>",
      "description": "需前台登入的路徑前綴，符合任一即要求 FRONT scope。"
    },
    {
      "name": "app.auth.guard.front-exclude-prefixes",
      "type": "java.util.List<java.lang.String>",
      "description": "自前台路徑排除的前綴（例如登入入口）。"
    },
    {
      "name": "app.auth.jwt.secret",
      "type": "java.lang.String",
      "description": "JWT HMAC 簽章用 secret（profile=jwt 時必填，至少 32 字元）。"
    },
    {
      "name": "app.cors.allowed-origins",
      "type": "java.util.List<java.lang.String>",
      "description": "允許跨域來源白名單。"
    },
    {
      "name": "app.cors.allow-credentials",
      "type": "java.lang.Boolean",
      "description": "是否允許攜帶憑證。"
    },
    {
      "name": "app.storage.provider",
      "type": "java.lang.String",
      "description": "儲存提供者（local/s3）。"
    },
    {
      "name": "app.storage.local.base-path",
      "type": "java.lang.String",
      "description": "本地儲存根目錄。"
    },
    {
      "name": "app.storage.local.public-base-url",
      "type": "java.lang.String",
      "description": "本地檔案公開 URL 前綴。"
    },
    {
      "name": "app.storage.s3.endpoint",
      "type": "java.lang.String",
      "description": "S3 相容服務端點。"
    },
    {
      "name": "app.storage.s3.region",
      "type": "java.lang.String",
      "description": "S3 區域。"
    },
    {
      "name": "app.storage.s3.bucket",
      "type": "java.lang.String",
      "description": "S3 Bucket 名稱。"
    },
    {
      "name": "app.audit.enabled",
      "type": "java.lang.Boolean",
      "description": "是否啟用稽核日誌。"
    },
    {
      "name": "app.audit.sink",
      "type": "java.lang.String",
      "description": "稽核輸出目標：console（僅 log）或 db（寫入 audit_log 表）。"
    },
    {
      "name": "app.audit.include-request-body",
      "type": "java.lang.Boolean",
      "description": "稽核日誌是否記錄 request body。"
    },
    {
      "name": "app.audit.include-response-body",
      "type": "java.lang.Boolean",
      "description": "稽核日誌是否記錄 response body。"
    },
    {
      "name": "app.audit.max-body-length",
      "type": "java.lang.Integer",
      "description": "稽核日誌 body 最大記錄長度。"
    },
    {
      "name": "app.audit.mask-fields",
      "type": "java.util.List<java.lang.String>",
      "description": "稽核日誌需遮罩的欄位名稱清單。"
    },
    {
      "name": "app.startup.api-base-url",
      "type": "java.lang.String",
      "description": "選填；設定的話啟動 log 會印出「API 根路徑: {api-base-url}/api」（Zeabur 等部署可設 APP_STARTUP_API_BASE_URL）。"
    }
  ]
}
